{
    "type": "FeatureCollection",
    "name": "incidents",
    "crs": { "type": "name", "properties": { "name": "urn:ogc:def:crs:OGC:1.3:CRS84" } },
    "features": [
        {
            "type": "Feature", 
            "properties": { 
                "ID": 1,
                "NAME": "Maxim Gorky Central Park for Culture and Recreation",
                "DATE": "2022-05-03",
                "REF": "CCTV timestamp"
            }, 
            "geometry": { 
                "type": "MultiPoint", 
                "coordinates": [
                    [36.245435228443036, 50.0177357160156],
                    [36.244647461762916, 50.01624340794919],
                    [36.239440, 50.018456],
                    [36.243228, 50.019291],
                    [36.242708, 50.017823],
                    [36.240792, 50.017491]
                ]
            } 
        },
        {
            "type": "Feature", 
            "properties": { 
                "ID": 2,
                "NAME": "Palace of Labor",
                "DATE": "2022-03-02",
                "REF": "https://twitter.com/kyivindependent/status/1499005733077143553?lang=en"
            }, 
            "geometry": { 
                "type": "MultiPoint", 
                "coordinates": [
                    [36.23254099558125, 49.98897538602896],
                    [36.23233252976288, 49.98945251080527]
                ]
            } 
        },
        {
            "type": "Feature", 
            "properties": { 
                "ID": 11,
                "NAME": "Apartment Building",
                "DATE": "2022-07-11",
                "REF": "First hand account"
            }, 
            "geometry": { 
                "type": "Point", 
                "coordinates": [36.23664465789781, 49.987720482615224]
            } 
        },
        {
            "type": "Feature", 
            "properties": { 
                "ID": 13,
                "NAME": "Academy of Sciences"
            }, 
            "geometry": { 
                "type": "Point", 
                "coordinates": [36.237582, 49.997720]
            } 
        },
        {
            "type": "Feature", 
            "properties": { 
                "ID": 15,
                "NAME": "Faculty of Economics of Kharkiv National University",
                "DATE": "2022-03-02",
                "REF": "https://twitter.com/DAlperovitch/status/1498914132225048576"
            }, 
            "geometry": { 
                "type": "Point", 
                "coordinates": [36.23553648372453, 49.99937895398078]
            } 
        },
        {
            "type": "Feature", 
            "properties": { 
                "ID": 16,
                "NAME": "Kharkiv Regional State Administration",
                "DATE": "2022-03-01",
                "REF": "https://www.youtube.com/watch?v=C3lKIwk-_Xc"
            }, 
            "geometry": { 
                "type": "Point", 
                "coordinates": [36.236448625383815, 50.00420931571493]
            } 
        },
        {
            "type": "Feature", 
            "properties": { 
                "ID": 17,
                "NAME": "Market, Червоний",
                "DATE": "2022-04-20",
                "REF": "https://twitter.com/truth_about_war/status/1517076152950607872"
            }, 
            "geometry": { 
                "type": "Point", 
                "coordinates": [36.33648455283565, 50.024539085108316]
            } 
        },
        {
            "type": "Feature", 
            "properties": { 
                "ID": 22,
                "NAME": "Hospital",
                "DATE": "2022-04-06",
                "REF": "https://twitter.com/TpyxaNews/status/1511612543357394945"
            }, 
            "geometry": { 
                "type": "Point", 
                "coordinates": [36.36105422049836, 50.03860946315341]
            } 
        },
        {
            "type": "Feature", 
            "properties": { 
                "ID": 24,
                "NAME": "Train Station"
            }, 
            "geometry": { 
                "type": "Point", 
                "coordinates": [36.36025851266752, 50.019797144650184]
            } 
        },
        {
            "type": "Feature", 
            "properties": { 
                "ID": 25,
                "NAME": "Apartment Building"
            }, 
            "geometry": { 
                "type": "Point", 
                "coordinates": [36.36503249072156, 50.026326281896345]
            } 
        },
        {
            "type": "Feature", 
            "properties": { 
                "ID": 28,
                "NAME": "Elementary School"
            }, 
            "geometry": { 
                "type": "Point", 
                "coordinates": [36.35721088659814, 50.03745912242639]
            } 
        },
        {
            "type": "Feature", 
            "properties": { 
                "ID": 29,
                "NAME": "Apartment Building"
            }, 
            "geometry": { 
                "type": "Point", 
                "coordinates": [36.354444360004464, 50.03762871534753]
            } 
        },
        {
            "type": "Feature", 
            "properties": { 
                "ID": 30,
                "NAME": "Playground"
            }, 
            "geometry": { 
                "type": "Point", 
                "coordinates": [36.35328516758444, 50.03834703048654]
            } 
        },
        {
            "type": "Feature", 
            "properties": { 
                "ID": 31,
                "NAME": "Apartment Building"
            }, 
            "geometry": { 
                "type": "Point", 
                "coordinates": [36.34935753478901, 50.03801573443867]
            } 
        },
        {
            "type": "Feature", 
            "properties": { 
                "ID": 32,
                "NAME": "Shopping Area"
            }, 
            "geometry": { 
                "type": "Point", 
                "coordinates": [36.348131680247924, 50.0388785143991]
            } 
        },
        {
            "type": "Feature", 
            "properties": { 
                "ID": 33,
                "NAME": "Playground"
            }, 
            "geometry": { 
                "type": "Point", 
                "coordinates": [36.352414207830314, 50.04388727055481]
            } 
        },
        {
            "type": "Feature", 
            "properties": { 
                "ID": 34,
                "NAME": "Parking Lot"
            }, 
            "geometry": { 
                "type": "Point", 
                "coordinates": [36.35348905855776, 50.04460566601063]
            } 
        },
        {
            "type": "Feature", 
            "properties": { 
                "ID": 35,
                "NAME": "Church of Holy Great Martyr George",
                "DATE": "2022-03-01",
                "REF": "https://twitter.com/michaelh992/status/1501228054102052867"
            }, 
            "geometry": { 
                "type": "Point", 
                "coordinates": [36.34394931252348, 50.03886102260411]
            } 
        },
        {
            "type": "Feature", 
            "properties": { 
                "ID": 36,
                "NAME": "Cemetery"
            }, 
            "geometry": { 
                "type": "Point", 
                "coordinates": [36.33887205944451, 50.03581185765823]
            } 
        }        
    ]
}